{"total":1,"pageSize":13,"pageCount":1,"data":[{"title":"hexo的一些常用指令","uid":"54c69c844aef62ce7a85c8afa5b91acc","slug":"hexo","date":"2023-03-07T14:39:48.000Z","updated":"2023-03-08T11:44:58.402Z","comments":true,"path":"api/articles/hexo.json","cover":"/images/cover-1.jpg","text":" 文中内容以百度结果与自身实践结合产生..结合了笔者自身的一些理解..如有不对欢迎指正… hexo g || hexo generate..该命令执行后在hexo站点根目录下生成public文件夹… hexo d通过public文件夹在本地生成.deploy_git文件夹…并将编...","link":"","photos":[],"count_time":{"symbolsCount":411,"symbolsTime":"1 mins."},"categories":[],"tags":[{"name":"hexo","slug":"hexo","count":1,"path":"api/tags/hexo.json"}],"author":{"name":"雨中冒险","slug":"blog-author","avatar":"/images/QQ.jpg","link":"/","description":"I'm in love with a shootin' star </br> But she moves so fast when she falls then I'll be waitin'","socials":{"github":"https://github.com/Kictoriz","twitter":"","stackoverflow":"","wechat":"","qq":"","weibo":"","zhihu":"","csdn":"","juejin":"","customs":{}}}}]}